BotMother-1.0.0.dist-info/DESCRIPTION.rst
BotMother-1.0.0.dist-info/METADATA
BotMother-1.0.0.dist-info/RECORD
BotMother-1.0.0.dist-info/WHEEL
BotMother-1.0.0.dist-info/metadata.json
BotMother-1.0.0.dist-info/top_level.txt
botmother/Blueprint.py
botmother/BotConstructor.py
botmother/Conversation.py
botmother/__init__.py
botmother/exception/Exceptions.py
botmother/exception/__init__.py
